chaos_utils/__init__.py
chaos_utils/dict_utils.py
chaos_utils/dingtalk.py
chaos_utils/gitignore.py
chaos_utils/logging.py
chaos_utils/tarfile.py
chaos_utils/telegram.py
chaos_utils/text_utils.py
chaos_utils/wechat.py
chaos_utils-0.3.1.dist-info/METADATA
chaos_utils-0.3.1.dist-info/WHEEL
chaos_utils-0.3.1.dist-info/licenses/LICENSE
chaos_utils-0.3.1.dist-info/RECORD
