Metadata-Version: 2.4
Name: chaos-utils
Version: 0.3.1
Summary: Collection of handy utils written in Python 3
Project-URL: Homepage, https://github.com/ak1ra-lab/chaos-utils
Project-URL: Changelog, https://github.com/ak1ra-lab/chaos-utils/blob/master/CHANGELOG.md
Author-email: ak1ra <git@ak1ra.xyz>
License-Expression: MIT
License-File: LICENSE
Keywords: utils
Classifier: Development Status :: 4 - Beta
Classifier: Programming Language :: Python :: 3
Classifier: Programming Language :: Python :: 3 :: Only
Classifier: Programming Language :: Python :: 3.11
Classifier: Programming Language :: Python :: 3.12
Classifier: Programming Language :: Python :: 3.13
Requires-Python: >=3.11
Requires-Dist: chardet>=5.2.0
Requires-Dist: httpx>=0.28.1
Requires-Dist: pathspec>=0.12.1
Requires-Dist: pyzstd>=0.17.0
